scilens_img/plugin.py
scilens_img/reader_img.py
scilens_img-0.1.4.dist-info/METADATA
scilens_img-0.1.4.dist-info/WHEEL
scilens_img-0.1.4.dist-info/entry_points.txt
scilens_img-0.1.4.dist-info/RECORD
